jsone/AST.py
jsone/__init__.py
jsone/builtins.py
jsone/interpreter.py
jsone/parser.py
jsone/render.py
jsone/shared.py
jsone/six.py
json_e-4.8.1.dist-info/METADATA
json_e-4.8.1.dist-info/WHEEL
json_e-4.8.1.dist-info/top_level.txt
json_e-4.8.1.dist-info/RECORD
