Metadata-Version: 2.4
Name: json-e
Version: 4.8.1
Summary: A data-structure parameterization system written for embedding context in JSON objects
Home-page: https://json-e.js.org
Author: Dustin J. Mitchell
Author-email: dustin@mozilla.com
License: MPL2
Provides-Extra: release
Requires-Dist: towncrier; extra == "release"
Dynamic: author
Dynamic: author-email
Dynamic: description
Dynamic: home-page
Dynamic: license
Dynamic: provides-extra
Dynamic: summary
